{
  "time": "3 minutes",
  "title": "Introduction to the Course",
  "details": {
    "intro": {
      "background": "background.sh",
      "foreground": "foreground.sh",
      "text": "intro.md"
    },
    "steps": [
      {
        "text": "step1.md"
      }
    ],
    "finish": {
      "text": "finish.md"
    },
    "assets": {
      "host01": [
        {
          "file": "start",
          "target": "/usr/local/bin/",
          "chmod": "+x"
        },
        {
          "file": "finish",
          "target": "/usr/local/bin/",
          "chmod": "+x"
        },
        {
          "file": "samplefile.txt",
          "target": "/root/editor"
        }
      ]
    }
  },
  "environment": {
    "uilayout": "editor-terminal",
    "uieditorpath": "/root/editor"
  },
  "backend": {
    "imageid": "datadog-base-v3",
    "reuseConnection": "false"
  }
}
